prixCarburantClient/prixCarburantClient.py
Prix_Carburant_FR_rmickael62_Client-0.0.2.dist-info/METADATA
Prix_Carburant_FR_rmickael62_Client-0.0.2.dist-info/WHEEL
Prix_Carburant_FR_rmickael62_Client-0.0.2.dist-info/entry_points.txt
Prix_Carburant_FR_rmickael62_Client-0.0.2.dist-info/top_level.txt
Prix_Carburant_FR_rmickael62_Client-0.0.2.dist-info/RECORD
