Metadata-Version: 2.1
Name: Prix-Carburant-FR-rmickael62-Client
Version: 0.0.2
Summary: StationEssence client by Rmickael62
Home-page: https://github.com/rmickael62/essence
Author: Maxime Wantiez, Yann RITTER
Author-email: 
License: MIT
Platform: UNKNOWN
